cobbler/__init__.py
cobbler/api.py
cobbler/autoinstall_manager.py
cobbler/autoinstallgen.py
cobbler/cexceptions.py
cobbler/cli.py
cobbler/cobblerd.py
cobbler/configgen.py
cobbler/decorator.py
cobbler/download_manager.py
cobbler/enums.py
cobbler/grub.py
cobbler/manager.py
cobbler/module_loader.py
cobbler/power_manager.py
cobbler/remote.py
cobbler/serializer.py
cobbler/services.py
cobbler/templar.py
cobbler/template_api.py
cobbler/tftpgen.py
cobbler/utils.py
cobbler/validate.py
cobbler/yumgen.py
cobbler/actions/__init__.py
cobbler/actions/acl.py
cobbler/actions/check.py
cobbler/actions/hardlink.py
cobbler/actions/log.py
cobbler/actions/mkloaders.py
cobbler/actions/replicate.py
cobbler/actions/report.py
cobbler/actions/reposync.py
cobbler/actions/status.py
cobbler/actions/sync.py
cobbler/actions/buildiso/__init__.py
cobbler/actions/buildiso/netboot.py
cobbler/actions/buildiso/standalone.py
cobbler/cobbler_collections/__init__.py
cobbler/cobbler_collections/collection.py
cobbler/cobbler_collections/distros.py
cobbler/cobbler_collections/files.py
cobbler/cobbler_collections/images.py
cobbler/cobbler_collections/manager.py
cobbler/cobbler_collections/menus.py
cobbler/cobbler_collections/mgmtclasses.py
cobbler/cobbler_collections/packages.py
cobbler/cobbler_collections/profiles.py
cobbler/cobbler_collections/repos.py
cobbler/cobbler_collections/systems.py
cobbler/items/__init__.py
cobbler/items/distro.py
cobbler/items/file.py
cobbler/items/image.py
cobbler/items/item.py
cobbler/items/menu.py
cobbler/items/mgmtclass.py
cobbler/items/package.py
cobbler/items/profile.py
cobbler/items/repo.py
cobbler/items/resource.py
cobbler/items/system.py
cobbler/modules/__init__.py
cobbler/modules/nsupdate_add_system_post.py
cobbler/modules/nsupdate_delete_system_pre.py
cobbler/modules/scm_track.py
cobbler/modules/sync_post_restart_services.py
cobbler/modules/sync_post_wingen.py
cobbler/modules/authentication/__init__.py
cobbler/modules/authentication/configfile.py
cobbler-3.3.7.dist-info/AUTHORS.in
cobbler-3.3.7.dist-info/COPYING
cobbler-3.3.7.dist-info/METADATA
cobbler-3.3.7.dist-info/WHEEL
cobbler-3.3.7.dist-info/top_level.txt
cobbler-3.3.7.dist-info/RECORD
