Metadata-Version: 2.1
Name: cobbler
Version: 3.3.7
Summary: Network Boot and Update Server
Home-page: UNKNOWN
Author: Team Cobbler
Author-email: cobbler.project@gmail.com
License: GPLv2+
Project-URL: Website, https://cobbler.github.io
Project-URL: Documentation (Users), https://cobbler.readthedocs.io/en/latest
Project-URL: Documentation (Devs), https://github.com/cobbler/cobbler/wiki
Project-URL: Source, https://github.com/cobbler/cobbler
Project-URL: Tracker, https://github.com/cobbler/cobbler/issues
Platform: UNKNOWN
License-File: COPYING
License-File: AUTHORS.in
Requires-Dist: mod-wsgi
Requires-Dist: requests
Requires-Dist: pyyaml
Requires-Dist: netaddr
Requires-Dist: Cheetah3
Requires-Dist: pymongo
Requires-Dist: distro
Requires-Dist: python-ldap
Requires-Dist: dnspython
Requires-Dist: file-magic
Requires-Dist: schema
Provides-Extra: changelog
Requires-Dist: towncrier>=22.8.0; extra == "changelog"
Provides-Extra: docs
Requires-Dist: sphinx; extra == "docs"
Requires-Dist: sphinx-rtd-theme; extra == "docs"
Requires-Dist: sphinxcontrib-apidoc; extra == "docs"
Provides-Extra: lint
Requires-Dist: pyflakes; extra == "lint"
Requires-Dist: pycodestyle; extra == "lint"
Requires-Dist: pylint; extra == "lint"
Requires-Dist: black; extra == "lint"
Requires-Dist: mypy; extra == "lint"
Provides-Extra: test
Requires-Dist: pytest>6; extra == "test"
Requires-Dist: pytest-cov; extra == "test"
Requires-Dist: codecov; extra == "test"
Requires-Dist: pytest-mock; extra == "test"
Requires-Dist: pytest-benchmark; extra == "test"
